{"layer": 2, "free boohoo delivery": {"free delivery boohoo code": 100, "boohoo code": 99, "boohoo delivery code": 99, "boohoo free next day delivery": 35, "free next day delivery": 35, "boohoo discount code free delivery": 25, "boohoo discount code": 24, "boohoo free next day delivery code": 16, "boohoo next day delivery code": 15, "boohoo codes": 12, "boohoo free delivery codes": 12, "boohoo promo code": 11, "boohoo free delivery promo code": 11, "asos": 10, "boohoo voucher code": 8, "boohoo free delivery code 2019": 7, "boohoo free delivery voucher code": 7, "pretty little thing": 7, "new look": 7, "missguided": 5, "boohoo free delivery code uk": 5, "boohoo discount codes": 5, "boohoo student discount": 4, "unidays": 4, "boohoo free delivery code 2018": 4}}