{"layer": 2, "iceland online shopping delivery": {"tesco": 100, "asda": 98, "tesco online shopping": 96, "asda online": 95, "tesco delivery": 95, "asda delivery": 94, "tesco online delivery": 93, "asda online shopping": 91, "morrisons online delivery": 76, "morrisons online": 74, "iceland online shopping home delivery": 73, "morrisons online shopping": 71, "iceland home delivery": 69, "morrisons": 69, "sainsburys online": 47, "sainsburys": 46, "sainsburys online shopping": 44, "iceland online shopping delivery slots": 37, "tesco home delivery": 32, "asda home delivery": 29, "morrisons delivery slots": 22, "iceland delivery slot": 19, "sainsburys home delivery": 17, "ocado": 16, "iceland deliveries": 10}}