{"layer": 2, "pizza deals": {"pizza hut": 100, "pizza hut deals": 100, "dominos pizza deals": 56, "dominos": 54, "dominos deals": 54, "dominos pizza": 54, "pizza express deals": 29, "pizza express": 28, "pizza delivery deals": 19, "pizza delivery": 18, "pizza deals uk": 15, "pizza hut delivery": 15, "pizza hut delivery deals": 14, "pizza near me": 12, "pizza deals near me": 11, "papa johns deals": 11, "papa johns": 11, "pizza hut uk deals": 8, "pizza hut uk": 8, "dominoes pizza": 8, "dominoes pizza deals": 7, "dominoes": 7, "dominoes deals": 7, "takeaway pizza deals": 7, "takeaway deals": 7}}