{"layer": 2, "pizza hut express": {"pizza hut express menu": 100, "pizza express menu": 96, "pizza hut menu": 94, "pizza hut delivery": 74, "pizza express delivery": 72, "dominos": 60, "dominos pizza": 56, "pizza near me": 43, "pizza hut near me": 43, "pizza express near me": 41, "pizza express voucher": 40, "pizza hut uk": 36, "pizza hut vouchers": 36, "pizza express vouchers": 34, "pizza hut takeaway": 26, "pizza hut deals": 24, "pizza hut restaurant": 24, "papa johns": 24, "pizza express takeaway": 23, "pizza express offers": 21, "pizza hut offers": 21, "just eat": 19, "pizza express discount": 18, "pizza hut buffet": 13, "dominoes": 13}}