{"layer": 2, "track royal mail": {"track trace": 100, "track trace royal mail": 99, "track and trace": 91, "track parcel": 57, "royal mail parcel track": 56, "royal mail tracking": 47, "track my royal mail": 34, "royal mail delivery": 20, "royal mail track delivery": 20, "track delivery": 19, "track my parcel": 18, "track my royal mail parcel": 18, "track post royal mail": 17, "track royal mail item": 13, "royal mail track a parcel": 12, "how to track royal mail": 12, "royal mail track order": 12, "track a parcel": 12, "royal mail parcel tracking": 10, "parcel tracking": 10, "post office track": 9, "track package royal mail": 8, "track package": 8, "parcelforce": 7, "track parcelforce": 7}}